pystrict.py
pystrict-1.3.dist-info/LICENSE
pystrict-1.3.dist-info/WHEEL
pystrict-1.3.dist-info/METADATA
pystrict-1.3.dist-info/RECORD
