Metadata-Version: 2.1
Name: pystrict
Version: 1.3
Summary: ## strict
Home-page: https://github.com/earonesty/pystrict
Author: Erik Aronesty
Author-email: erik@q32.com
Requires-Python: >=3.6
Classifier: Intended Audience :: Developers
Classifier: License :: OSI Approved :: MIT License
Classifier: Programming Language :: Python
Classifier: Topic :: Software Development :: Libraries :: Python Modules
